refined_claude/__init__.py
refined_claude/__main__.py
refined_claude/accessibility.py
refined_claude/accessibility_api.py
refined_claude/cli.py
refined_claude/console.py
refined_claude/fake_accessibility.py
refined_claude/features.py
refined_claude/logging.py
refined_claude/parsing.py
refined_claude/snapshot.py
refined_claude/test_base.py
refined_claude/ui.py
refined_claude-0.2.0.dist-info/METADATA
refined_claude-0.2.0.dist-info/WHEEL
refined_claude-0.2.0.dist-info/entry_points.txt
refined_claude-0.2.0.dist-info/licenses/LICENSE
refined_claude-0.2.0.dist-info/RECORD
