Metadata-Version: 2.4
Name: refined-claude
Version: 0.2.0
Summary: Accessibility refinements to Claude Desktop
Project-URL: Homepage, https://github.com/ezyang/refined-claude
Project-URL: Changelog, https://github.com/ezyang/refined-claude/releases
Project-URL: Issues, https://github.com/ezyang/refined-claude/issues
Project-URL: CI, https://github.com/ezyang/refined-claude/actions
Author: Edward Z. Yang
License: Apache-2.0
License-File: LICENSE
Classifier: License :: OSI Approved :: Apache Software License
Requires-Python: >=3.12
Requires-Dist: click
Requires-Dist: pyobjc-core==10.3.2
Requires-Dist: pyobjc-framework-applicationservices==10.3.2
Requires-Dist: pyobjc-framework-cocoa==10.3.2
Requires-Dist: pyobjc-framework-quartz==10.3.2
Requires-Dist: rich>=13.9.4
